distry/__init__.py
distry/client.py
distry/exceptions.py
distry/worker.py
distry_py-0.2.1.dist-info/licenses/LICENSE
distry_py-0.2.1.dist-info/METADATA
distry_py-0.2.1.dist-info/WHEEL
distry_py-0.2.1.dist-info/entry_points.txt
distry_py-0.2.1.dist-info/top_level.txt
distry_py-0.2.1.dist-info/RECORD
