Metadata-Version: 2.4
Name: distry-py
Version: 0.2.1
Summary: Distributed task execution framework
Author: Carlo Moro
License: MIT
Project-URL: Homepage, https://github.com/cnmoro/distry
Keywords: distributed,computing,parallel,processing
Classifier: Development Status :: 4 - Beta
Classifier: Intended Audience :: Developers
Classifier: License :: OSI Approved :: MIT License
Classifier: Programming Language :: Python :: 3
Classifier: Programming Language :: Python :: 3.8
Classifier: Programming Language :: Python :: 3.9
Classifier: Programming Language :: Python :: 3.10
Classifier: Programming Language :: Python :: 3.11
Requires-Python: >=3.8
License-File: LICENSE
Provides-Extra: client
Requires-Dist: requests; extra == "client"
Requires-Dist: cloudpickle; extra == "client"
Provides-Extra: worker
Requires-Dist: fastapi; extra == "worker"
Requires-Dist: uvicorn[standard]; extra == "worker"
Requires-Dist: cloudpickle; extra == "worker"
Requires-Dist: pydantic; extra == "worker"
Provides-Extra: dev
Requires-Dist: pytest; extra == "dev"
Requires-Dist: pytest-asyncio; extra == "dev"
Requires-Dist: requests; extra == "dev"
Requires-Dist: black; extra == "dev"
Requires-Dist: flake8; extra == "dev"
Requires-Dist: mypy; extra == "dev"
Provides-Extra: all
Requires-Dist: requests; extra == "all"
Requires-Dist: cloudpickle; extra == "all"
Requires-Dist: fastapi; extra == "all"
Requires-Dist: uvicorn[standard]; extra == "all"
Requires-Dist: cloudpickle; extra == "all"
Requires-Dist: pydantic; extra == "all"
Dynamic: license-file
